{"nodes": [{"id": "c_users_sales_claudee_expressrepairs_repo_superpowers_sdd_task_3_report_md", "label": "task-3-report.md", "file_type": "document", "source_file": ".superpowers/sdd/task-3-report.md", "source_location": "L1"}, {"id": "sdd_task_3_report_task_3_report_landing_lead_helpers_landingform_island", "label": "Task 3 Report: Landing lead helpers + LandingForm island", "file_type": "document", "source_file": ".superpowers/sdd/task-3-report.md", "source_location": "L1"}, {"id": "sdd_task_3_report_status", "label": "Status", "file_type": "document", "source_file": ".superpowers/sdd/task-3-report.md", "source_location": "L3"}, {"id": "sdd_task_3_report_implementation_summary", "label": "Implementation Summary", "file_type": "document", "source_file": ".superpowers/sdd/task-3-report.md", "source_location": "L6"}, {"id": "sdd_task_3_report_files_created", "label": "Files Created", "file_type": "document", "source_file": ".superpowers/sdd/task-3-report.md", "source_location": "L8"}, {"id": "sdd_task_3_report_tdd_evidence", "label": "TDD Evidence", "file_type": "document", "source_file": ".superpowers/sdd/task-3-report.md", "source_location": "L26"}, {"id": "sdd_task_3_report_step_1_2_test_fails_red", "label": "Step 1-2: Test Fails (RED)", "file_type": "document", "source_file": ".superpowers/sdd/task-3-report.md", "source_location": "L28"}, {"id": "sdd_task_3_report_step_3_4_test_passes_green", "label": "Step 3-4: Test Passes (GREEN)", "file_type": "document", "source_file": ".superpowers/sdd/task-3-report.md", "source_location": "L35"}, {"id": "sdd_task_3_report_step_5_6_full_suite_passes_build", "label": "Step 5-6: Full Suite Passes (BUILD)", "file_type": "document", "source_file": ".superpowers/sdd/task-3-report.md", "source_location": "L48"}, {"id": "sdd_task_3_report_git_commit", "label": "Git Commit", "file_type": "document", "source_file": ".superpowers/sdd/task-3-report.md", "source_location": "L72"}, {"id": "sdd_task_3_report_design_decisions", "label": "Design Decisions", "file_type": "document", "source_file": ".superpowers/sdd/task-3-report.md", "source_location": "L77"}, {"id": "sdd_task_3_report_phone_regex", "label": "Phone Regex", "file_type": "document", "source_file": ".superpowers/sdd/task-3-report.md", "source_location": "L79"}, {"id": "sdd_task_3_report_honeypot_field", "label": "Honeypot Field", "file_type": "document", "source_file": ".superpowers/sdd/task-3-report.md", "source_location": "L82"}, {"id": "sdd_task_3_report_component_state", "label": "Component State", "file_type": "document", "source_file": ".superpowers/sdd/task-3-report.md", "source_location": "L85"}, {"id": "sdd_task_3_report_accessibility", "label": "Accessibility", "file_type": "document", "source_file": ".superpowers/sdd/task-3-report.md", "source_location": "L89"}, {"id": "sdd_task_3_report_event_dispatch", "label": "Event Dispatch", "file_type": "document", "source_file": ".superpowers/sdd/task-3-report.md", "source_location": "L95"}, {"id": "sdd_task_3_report_testing_approach", "label": "Testing Approach", "file_type": "document", "source_file": ".superpowers/sdd/task-3-report.md", "source_location": "L98"}, {"id": "sdd_task_3_report_self_review", "label": "Self-Review", "file_type": "document", "source_file": ".superpowers/sdd/task-3-report.md", "source_location": "L107"}, {"id": "sdd_task_3_report_what_worked", "label": "What Worked", "file_type": "document", "source_file": ".superpowers/sdd/task-3-report.md", "source_location": "L109"}, {"id": "sdd_task_3_report_what_could_improve", "label": "What Could Improve", "file_type": "document", "source_file": ".superpowers/sdd/task-3-report.md", "source_location": "L116"}, {"id": "sdd_task_3_report_concerns", "label": "Concerns", "file_type": "document", "source_file": ".superpowers/sdd/task-3-report.md", "source_location": "L121"}, {"id": "sdd_task_3_report_files_changed", "label": "Files Changed", "file_type": "document", "source_file": ".superpowers/sdd/task-3-report.md", "source_location": "L124"}], "edges": [{"source": "c_users_sales_claudee_expressrepairs_repo_superpowers_sdd_task_3_report_md", "target": "sdd_task_3_report_task_3_report_landing_lead_helpers_landingform_island", "relation": "contains", "confidence": "EXTRACTED", "source_file": ".superpowers/sdd/task-3-report.md", "source_location": "L1", "weight": 1.0}, {"source": "sdd_task_3_report_task_3_report_landing_lead_helpers_landingform_island", "target": "sdd_task_3_report_status", "relation": "contains", "confidence": "EXTRACTED", "source_file": ".superpowers/sdd/task-3-report.md", "source_location": "L3", "weight": 1.0}, {"source": "sdd_task_3_report_task_3_report_landing_lead_helpers_landingform_island", "target": "sdd_task_3_report_implementation_summary", "relation": "contains", "confidence": "EXTRACTED", "source_file": ".superpowers/sdd/task-3-report.md", "source_location": "L6", "weight": 1.0}, {"source": "sdd_task_3_report_implementation_summary", "target": "sdd_task_3_report_files_created", "relation": "contains", "confidence": "EXTRACTED", "source_file": ".superpowers/sdd/task-3-report.md", "source_location": "L8", "weight": 1.0}, {"source": "sdd_task_3_report_implementation_summary", "target": "sdd_task_3_report_tdd_evidence", "relation": "contains", "confidence": "EXTRACTED", "source_file": ".superpowers/sdd/task-3-report.md", "source_location": "L26", "weight": 1.0}, {"source": "sdd_task_3_report_tdd_evidence", "target": "sdd_task_3_report_step_1_2_test_fails_red", "relation": "contains", "confidence": "EXTRACTED", "source_file": ".superpowers/sdd/task-3-report.md", "source_location": "L28", "weight": 1.0}, {"source": "sdd_task_3_report_tdd_evidence", "target": "sdd_task_3_report_step_3_4_test_passes_green", "relation": "contains", "confidence": "EXTRACTED", "source_file": ".superpowers/sdd/task-3-report.md", "source_location": "L35", "weight": 1.0}, {"source": "sdd_task_3_report_tdd_evidence", "target": "sdd_task_3_report_step_5_6_full_suite_passes_build", "relation": "contains", "confidence": "EXTRACTED", "source_file": ".superpowers/sdd/task-3-report.md", "source_location": "L48", "weight": 1.0}, {"source": "sdd_task_3_report_implementation_summary", "target": "sdd_task_3_report_git_commit", "relation": "contains", "confidence": "EXTRACTED", "source_file": ".superpowers/sdd/task-3-report.md", "source_location": "L72", "weight": 1.0}, {"source": "sdd_task_3_report_task_3_report_landing_lead_helpers_landingform_island", "target": "sdd_task_3_report_design_decisions", "relation": "contains", "confidence": "EXTRACTED", "source_file": ".superpowers/sdd/task-3-report.md", "source_location": "L77", "weight": 1.0}, {"source": "sdd_task_3_report_design_decisions", "target": "sdd_task_3_report_phone_regex", "relation": "contains", "confidence": "EXTRACTED", "source_file": ".superpowers/sdd/task-3-report.md", "source_location": "L79", "weight": 1.0}, {"source": "sdd_task_3_report_design_decisions", "target": "sdd_task_3_report_honeypot_field", "relation": "contains", "confidence": "EXTRACTED", "source_file": ".superpowers/sdd/task-3-report.md", "source_location": "L82", "weight": 1.0}, {"source": "sdd_task_3_report_design_decisions", "target": "sdd_task_3_report_component_state", "relation": "contains", "confidence": "EXTRACTED", "source_file": ".superpowers/sdd/task-3-report.md", "source_location": "L85", "weight": 1.0}, {"source": "sdd_task_3_report_design_decisions", "target": "sdd_task_3_report_accessibility", "relation": "contains", "confidence": "EXTRACTED", "source_file": ".superpowers/sdd/task-3-report.md", "source_location": "L89", "weight": 1.0}, {"source": "sdd_task_3_report_design_decisions", "target": "sdd_task_3_report_event_dispatch", "relation": "contains", "confidence": "EXTRACTED", "source_file": ".superpowers/sdd/task-3-report.md", "source_location": "L95", "weight": 1.0}, {"source": "sdd_task_3_report_task_3_report_landing_lead_helpers_landingform_island", "target": "sdd_task_3_report_testing_approach", "relation": "contains", "confidence": "EXTRACTED", "source_file": ".superpowers/sdd/task-3-report.md", "source_location": "L98", "weight": 1.0}, {"source": "sdd_task_3_report_task_3_report_landing_lead_helpers_landingform_island", "target": "sdd_task_3_report_self_review", "relation": "contains", "confidence": "EXTRACTED", "source_file": ".superpowers/sdd/task-3-report.md", "source_location": "L107", "weight": 1.0}, {"source": "sdd_task_3_report_self_review", "target": "sdd_task_3_report_what_worked", "relation": "contains", "confidence": "EXTRACTED", "source_file": ".superpowers/sdd/task-3-report.md", "source_location": "L109", "weight": 1.0}, {"source": "sdd_task_3_report_self_review", "target": "sdd_task_3_report_what_could_improve", "relation": "contains", "confidence": "EXTRACTED", "source_file": ".superpowers/sdd/task-3-report.md", "source_location": "L116", "weight": 1.0}, {"source": "sdd_task_3_report_self_review", "target": "sdd_task_3_report_concerns", "relation": "contains", "confidence": "EXTRACTED", "source_file": ".superpowers/sdd/task-3-report.md", "source_location": "L121", "weight": 1.0}, {"source": "sdd_task_3_report_task_3_report_landing_lead_helpers_landingform_island", "target": "sdd_task_3_report_files_changed", "relation": "contains", "confidence": "EXTRACTED", "source_file": ".superpowers/sdd/task-3-report.md", "source_location": "L124", "weight": 1.0}], "input_tokens": 0, "output_tokens": 0}